annorefine-2025.9.18.dist-info/METADATA
annorefine-2025.9.18.dist-info/WHEEL
annorefine-2025.9.18.dist-info/licenses/LICENSE
annorefine/__init__.py
annorefine/_annorefine.cpython-39-darwin.so
annorefine-2025.9.18.dist-info/RECORD
