Metadata-Version: 2.4
Name: annorefine
Version: 2025.9.18
Classifier: Development Status :: 4 - Beta
Classifier: Intended Audience :: Science/Research
Classifier: License :: OSI Approved :: MIT License
Classifier: Programming Language :: Python :: 3
Classifier: Programming Language :: Python :: 3.8
Classifier: Programming Language :: Python :: 3.9
Classifier: Programming Language :: Python :: 3.10
Classifier: Programming Language :: Python :: 3.11
Classifier: Programming Language :: Python :: 3.12
Classifier: Programming Language :: Python :: 3.13
Classifier: Programming Language :: Rust
Classifier: Topic :: Scientific/Engineering :: Bio-Informatics
Requires-Dist: pytest>=6.0 ; extra == 'dev'
Requires-Dist: pytest-cov ; extra == 'dev'
Requires-Dist: black ; extra == 'dev'
Requires-Dist: isort ; extra == 'dev'
Requires-Dist: mypy ; extra == 'dev'
Requires-Dist: pre-commit ; extra == 'dev'
Provides-Extra: dev
License-File: LICENSE
Summary: Genome annotation refinement using RNA-seq data
Keywords: bioinformatics,genomics,annotation,rna-seq
Home-Page: https://github.com/nextgenusfs/annorefine
Author-email: Jon Palmer <nextgenusfs@gmail.com>
License: MIT
Requires-Python: >=3.9
Project-URL: Bug Reports, https://github.com/nextgenusfs/annorefine/issues
Project-URL: Source, https://github.com/nextgenusfs/annorefine
